odoo/addons/website_event_require_login/README.rst
odoo/addons/website_event_require_login/__init__.py
odoo/addons/website_event_require_login/__manifest__.py
odoo/addons/website_event_require_login/controllers/__init__.py
odoo/addons/website_event_require_login/controllers/main.py
odoo/addons/website_event_require_login/i18n/es.po
odoo/addons/website_event_require_login/i18n/it.po
odoo/addons/website_event_require_login/i18n/website_event_require_login.pot
odoo/addons/website_event_require_login/models/__init__.py
odoo/addons/website_event_require_login/models/event.py
odoo/addons/website_event_require_login/readme/CONFIGURE.rst
odoo/addons/website_event_require_login/readme/CONTRIBUTORS.rst
odoo/addons/website_event_require_login/readme/DESCRIPTION.rst
odoo/addons/website_event_require_login/readme/ROADMAP.rst
odoo/addons/website_event_require_login/readme/USAGE.rst
odoo/addons/website_event_require_login/static/description/icon.png
odoo/addons/website_event_require_login/static/description/index.html
odoo/addons/website_event_require_login/views/event_views.xml
odoo/addons/website_event_require_login/views/website_event_templates.xml
odoo13_addon_website_event_require_login-13.0.1.0.1.dev7.dist-info/METADATA
odoo13_addon_website_event_require_login-13.0.1.0.1.dev7.dist-info/WHEEL
odoo13_addon_website_event_require_login-13.0.1.0.1.dev7.dist-info/top_level.txt
odoo13_addon_website_event_require_login-13.0.1.0.1.dev7.dist-info/RECORD
